agentauth_sdk/__init__.py
agentauth_sdk/client.py
agentauth_sdk/permissions.py
agentauth_sdk/types.py
agentauth_sdk/utils.py
umytbaynazarow_agentauth_sdk-0.1.2.dist-info/METADATA
umytbaynazarow_agentauth_sdk-0.1.2.dist-info/WHEEL
umytbaynazarow_agentauth_sdk-0.1.2.dist-info/top_level.txt
umytbaynazarow_agentauth_sdk-0.1.2.dist-info/RECORD
